CHANGES
LICENSE
MANIFEST.in
README.rst
setup.py
django_appypod.egg-info/PKG-INFO
django_appypod.egg-info/SOURCES.txt
django_appypod.egg-info/dependency_links.txt
django_appypod.egg-info/not-zip-safe
django_appypod.egg-info/requires.txt
django_appypod.egg-info/top_level.txt
djappypod/__init__.py
djappypod/backend.py
djappypod/response.py