Metadata-Version: 1.1
Name: django-appypod
Version: 2.0.6
Summary: Render OpenDocument files from templates, using Appy POD
Home-page: https://github.com/makinacorpus/django-appypod/
Author: Mathieu Leplatre
Author-email: mathieu.leplatre@makina-corpus.com
License: LPGL, see LICENSE file.
Download-URL: http://pypi.python.org/pypi/django-appypod/
Platform: UNKNOWN
Classifier: Topic :: Utilities
Classifier: Natural Language :: English
Classifier: Operating System :: OS Independent
Classifier: Intended Audience :: Developers
Classifier: Environment :: Web Environment
Classifier: Framework :: Django
Classifier: Development Status :: 5 - Production/Stable
Classifier: Programming Language :: Python :: 3.5
